simpleValidatorForConsoleApp/__init__.py
simpleValidatorForConsoleApp/validator.py
simplevalidatorforconsoleapp-1.2.dist-info/licenses/LICENSE
simplevalidatorforconsoleapp-1.2.dist-info/METADATA
simplevalidatorforconsoleapp-1.2.dist-info/WHEEL
simplevalidatorforconsoleapp-1.2.dist-info/top_level.txt
simplevalidatorforconsoleapp-1.2.dist-info/RECORD
