Metadata-Version: 2.4
Name: simpleValidatorForConsoleApp
Version: 1.2
Summary: A small validator for console applications
Author: Dougu77
License-Expression: MIT
Project-URL: Homepage, https://github.com/Dougu77/simple-validator
Project-URL: Issues, https://github.com/Dougu77/simple-validator/issues
Classifier: Programming Language :: Python :: 3
Classifier: Operating System :: OS Independent
Requires-Python: >=3.9
License-File: LICENSE
Dynamic: license-file
